{
  "board": {
    "size": "8x8",
    "files": ["a", "b", "c", "d", "e", "f", "g", "h"],
    "ranks": [1, 2, 3, 4, 5, 6, 7, 8],
    "note": "The lower-right square (from White's perspective) is always light (h1)."
  },
  "pieces": [
    {
      "id": "pawn",
      "name": "Pawn",
      "symbol_white": "♙",
      "symbol_black": "♟",
      "image_white": "images/pawn_white.png",
      "image_black": "images/pawn_black.png",
      "movement": {
        "advance": {
          "normal": "1 square forward",
          "first_move": "optionally 2 squares forward if not moved yet"
        },
        "capture": "1 square diagonally forward (left or right)",
        "cannot_move_backward": true,
        "special_captures": ["en_passant"]
      },
      "promotion": {
        "when": "upon reaching the opposite end of the board (rank 8 for White, rank 1 for Black)",
        "options": ["Queen", "Rook", "Bishop", "Knight"],
        "default_recommendation": "Queen"
      },
      "examples": [
        {"position": "e2 -> e3", "notes": "normal advance"},
        {"position": "e2 -> e4", "notes": "double advance on first move"},
        {"position": "d5 captures c6", "notes": "diagonal capture"}
      ]
    },
    {
      "id": "rook",
      "name": "Rook",
      "symbol_white": "♖",
      "symbol_black": "♜",
      "image_white": "images/rook_white.png",
      "image_black": "images/rook_black.png",
      "movement": {
        "type": "linear",
        "directions": ["horizontal", "vertical"],
        "range": "any number of squares without jumping over pieces"
      },
      "capture": "same as movement (occupies the enemy piece's square)",
      "examples": [
        {"position": "a1 -> a8", "notes": "moves vertically up the file"},
        {"position": "h4 -> d4", "notes": "moves horizontally across the rank"}
      ]
    },
    {
      "id": "knight",
      "name": "Knight",
      "symbol_white": "♘",
      "symbol_black": "♞",
      "image_white": "images/knight_white.png",
      "image_black": "images/knight_black.png",
      "movement": {
        "pattern": "L-shape",
        "details": "2 squares in one direction (horizontal or vertical) + 1 square perpendicular",
        "can_jump": true
      },
      "capture": "lands on and replaces the opponent's piece",
      "examples": [
        {"position": "g1 -> f3", "notes": "typical opening move for White"},
        {"position": "b1 -> c3", "notes": "another common knight jump"}
      ]
    },
    {
      "id": "bishop",
      "name": "Bishop",
      "symbol_white": "♗",
      "symbol_black": "♝",
      "image_white": "images/bishop_white.png",
      "image_black": "images/bishop_black.png",
      "movement": {
        "type": "diagonal",
        "range": "any number of squares diagonally without jumping",
        "color_bound": "remains on the same color of square it starts on"
      },
      "capture": "same as movement",
      "examples": [
        {"position": "c1 -> g5", "notes": "bishop moves along a diagonal"},
        {"position": "f8 -> a3", "notes": "long diagonal move"}
      ]
    },
    {
      "id": "queen",
      "name": "Queen",
      "symbol_white": "♕",
      "symbol_black": "♛",
      "image_white": "images/queen_white.png",
      "image_black": "images/queen_black.png",
      "movement": {
        "type": "combined",
        "details": "combines rook and bishop moves: horizontally, vertically, or diagonally",
        "range": "any number of squares without jumping"
      },
      "capture": "same as movement",
      "examples": [
        {"position": "d1 -> d4", "notes": "vertical move"},
        {"position": "d1 -> g4", "notes": "diagonal move"}
      ]
    },
    {
      "id": "king",
      "name": "King",
      "symbol_white": "♔",
      "symbol_black": "♚",
      "image_white": "images/king_white.png",
      "image_black": "images/king_black.png",
      "movement": {
        "type": "short",
        "details": "1 square in any direction (horizontal, vertical, diagonal)",
        "cannot_move_into_check": true
      },
      "capture": "moves onto the opponent's piece (if safe)",
      "special": ["castling"],
      "examples": [
        {"position": "e1 -> e2", "notes": "simple one-square move"},
        {"position": "e1 -> g1", "notes": "kingside castling"}
      ]
    }
  ],
  "special_rules": {
    "castling": {
      "names": ["kingside castling", "queenside castling"],
      "description": "A special move involving the king and a rook. The king moves two squares toward the rook, and the rook moves to the square next to the king on the opposite side.",
      "conditions": [
        "Neither the king nor the involved rook has moved before.",
        "No pieces between the king and rook.",
        "The king cannot be in check before, during, or after castling."
      ],
      "examples": [
        {"short": "White: king e1 + rook h1 -> king g1, rook f1"},
        {"long": "White: king e1 + rook a1 -> king c1, rook d1"}
      ]
    },
    "en_passant": {
      "description": "A special pawn capture available immediately after an opposing pawn advances two squares and lands beside your pawn.",
      "conditions": [
        "Can only be performed immediately after the opponent's double pawn move.",
        "The capturing pawn moves diagonally to the square the enemy pawn passed through."
      ],
      "example": "White pawn on e5, Black plays d7->d5; White can capture en passant on d6 only on the next move."
    },
    "promotion": {
      "description": "When a pawn reaches the final rank, it must be promoted to another piece (Queen, Rook, Bishop, or Knight) of the same color.",
      "notes": [
        "Promotion is mandatory.",
        "You may have multiple queens or other pieces."
      ],
      "example": "White pawn e7 -> e8 = Queen"
    },
    "draws": {
      "types": [
        {"stalemate": "The player has no legal moves and their king is not in check (draw)."},
        {"threefold_repetition": "The same position occurs three times with the same player to move; draw may be claimed."},
        {"fifty_move_rule": "Fifty consecutive moves without a pawn move or capture; draw may be claimed."}
      ]
    }
  },
  "notation_examples": {
    "algebraic": {
      "description": "Standard chess notation: piece letter (K,Q,R,B,N; pawns omit the letter) + destination square. 'x' means capture, '+' check, '#' checkmate.",
      "examples": [
        {"move": "e4", "meaning": "pawn to e4"},
        {"move": "Nf3", "meaning": "knight to f3"},
        {"move": "Bxe6", "meaning": "bishop captures on e6"},
        {"move": "O-O", "meaning": "kingside castling"},
        {"move": "O-O-O", "meaning": "queenside castling"}
      ]
    }
  },
  "usage_suggestions": {
    "practice": [
      "Place pieces on a board and practice each movement individually.",
      "Do drills: for example, move only knights for 10 minutes, then pawns, etc.",
      "Play short games to become familiar with the flow of play."
    ],
    "study_order_recommendation": [
      "1) Pawns and King (basic movement and promotion).",
      "2) Knight and Bishop (jumping and diagonals).",
      "3) Rook and Queen (long-range movement).",
      "4) Castling and en passant (special rules).",
      "5) Algebraic notation for recording games."
    ]
  },
  "metadata": {
    "language": "en",
    "generated_for": "user",
    "images_source_note": "Replace the 'images/...' URLs with your own asset paths or online chess icons (e.g., from Wikimedia or Lichess).",
    "purpose": "Structured JSON for use in tutorials, educational apps, or visualization tools."
  }
}

